Metadata-Version: 1.0
Name: fecloud
Version: 0.1.1
Summary: Backend Cloud Package
Home-page: UNKNOWN
Author: UNKNOWN
Author-email: UNKNOWN
License: UNKNOWN
Platform: UNKNOWN
